{
    "modelValue": {
        "comments": [
            "url for small images"
        ]
    },
    "inputElements": {
        "comments": [
            "url for large image"
        ]
    },
    "inputTypes": {
        "comments": [
            "url for large image"
        ]
    },
    "replaceInputType": {
        "comments": [
            "url for large image"
        ]
    },
    "useSlot": {
        "comments": [
            "url for large image"
        ]
    },
    "multipleSwitch": {
        "comments": [
            "url for large image"
        ]
    },
    "showLabel": {
        "comments": [
            "url for large image"
        ]
    },
    "labelText": {
        "comments": [
            "url for large image"
        ]
    },
    "labelInline": {
        "comments": [
            "url for large image"
        ]
    },
    "stretchHorizontally": {
        "comments": [
            "url for large image"
        ]
    }
}